birthdayWisher.py
birthdayWisher-0.0.1.dist-info/METADATA
birthdayWisher-0.0.1.dist-info/WHEEL
birthdayWisher-0.0.1.dist-info/top_level.txt
birthdayWisher-0.0.1.dist-info/RECORD
