Metadata-Version: 2.1
Name: birthdayWisher
Version: 0.0.1
Summary: A cool happy birthday wish flow!
Home-page: https://github.com/Victorspy-web/birthdayWisher
Author: VED
Author-email: dicksonsmart0711@gmail.com
License: UNKNOWN
Platform: UNKNOWN
Classifier: Operating System :: OS Independent
